{
  "mixcloudKey": "adventures-in-decent-music-volume-7-rod-temperton-special",
  "tracks": [
    {
      "publisher": "A&M Records",
      "startTime": "00:00",
      "trackName": "Turn The Action On",
      "artistName": "Quincy Jones",
      "coverArtDate": "2021-07-19 17:25:42",
      "coverArtLarge": "https://img.discogs.com/NY2Tg0t_Gl2pV06YvGhq1lXe4_4=/fit-in/600x600/filters:strip_icc():format(jpeg):mode_rgb():quality(90)/discogs-images/R-2761237-1391106802-2935.jpeg.jpg",
      "coverArtSmall": "https://img.discogs.com/Kh3fYl9SFNV-1nWwwBFAZoMowNM=/fit-in/150x150/filters:strip_icc():format(jpeg):mode_rgb():quality(40)/discogs-images/R-2761237-1391106802-2935.jpeg.jpg",
      "sectionNumber": 1,
      "remixArtistName": ""
    },
    {
      "publisher": "GTO",
      "startTime": "02:40",
      "trackName": "Boogie Nights",
      "artistName": "Heatwave",
      "coverArtDate": "2021-07-19 17:25:44",
      "coverArtLarge": "https://img.discogs.com/1wvimpaage5QpaWKPG2oMcDqUD0=/fit-in/400x405/filters:strip_icc():format(jpeg):mode_rgb():quality(90)/discogs-images/R-1452672-1220884435.jpeg.jpg",
      "coverArtSmall": "https://img.discogs.com/m1a81ndt3BVHoltEY6gynK629Kw=/fit-in/150x150/filters:strip_icc():format(jpeg):mode_rgb():quality(40)/discogs-images/R-1452672-1220884435.jpeg.jpg",
      "sectionNumber": 2,
      "remixArtistName": ""
    },
    {
      "publisher": "GTO",
      "startTime": "05:34",
      "trackName": "Put The Word Out",
      "artistName": "Heatwave",
      "coverArtDate": "2021-07-19 17:25:47",
      "coverArtLarge": "https://img.discogs.com/Y29QoWp8vKf3x_uqUYdk0bYJbWc=/fit-in/600x598/filters:strip_icc():format(jpeg):mode_rgb():quality(90)/discogs-images/R-490902-1458649116-9143.jpeg.jpg",
      "coverArtSmall": "https://img.discogs.com/lAV7PO_JVCQekfnjvQhsVlIP5wI=/fit-in/150x150/filters:strip_icc():format(jpeg):mode_rgb():quality(40)/discogs-images/R-490902-1458649116-9143.jpeg.jpg",
      "sectionNumber": 3,
      "remixArtistName": ""
    },
    {
      "publisher": "A&M Records",
      "startTime": "10:48",
      "trackName": "Stomp",
      "artistName": "Brothers Johnson",
      "coverArtDate": "2021-07-19 17:25:50",
      "coverArtLarge": "https://img.discogs.com/V0wdjVQ-w4BIULBlu81fWsaoBAE=/600x600/smart/filters:strip_icc():format(jpeg):mode_rgb():quality(90)/discogs-images/A-88606-1591255509-5868.jpeg.jpg",
      "coverArtSmall": "https://img.discogs.com/tOfdCOCSJHZj0ejlOvPR_G8Vxxw=/150x150/smart/filters:strip_icc():format(jpeg):mode_rgb():quality(40)/discogs-images/A-88606-1591255509-5868.jpeg.jpg",
      "sectionNumber": 4,
      "remixArtistName": ""
    },
    {
      "publisher": "GTO",
      "startTime": "14:10",
      "trackName": "Jitterbuggin'",
      "artistName": "Heatwave",
      "coverArtDate": "2021-07-19 17:25:52",
      "coverArtLarge": "https://img.discogs.com/IYH5XhDd3NKTJWrSuaSFSNa8HG8=/fit-in/600x600/filters:strip_icc():format(jpeg):mode_rgb():quality(90)/discogs-images/R-463390-1528482873-3291.jpeg.jpg",
      "coverArtSmall": "https://img.discogs.com/0wDNfjCucat6AKtigguHDlESQbw=/fit-in/150x150/filters:strip_icc():format(jpeg):mode_rgb():quality(40)/discogs-images/R-463390-1528482873-3291.jpeg.jpg",
      "sectionNumber": 5,
      "remixArtistName": ""
    },
    {
      "publisher": "CBS",
      "startTime": "17:05",
      "trackName": "The Bomb",
      "artistName": "Herbie Hancock",
      "coverArtDate": "2021-07-19 17:25:55",
      "coverArtLarge": "https://img.discogs.com/2qKWxK9jh7ed547gjxIcntsObYY=/fit-in/600x594/filters:strip_icc():format(jpeg):mode_rgb():quality(90)/discogs-images/R-1249070-1446504539-8960.jpeg.jpg",
      "coverArtSmall": "https://img.discogs.com/opTO7d8j0LgKUthBUkMlijUM8ow=/fit-in/150x150/filters:strip_icc():format(jpeg):mode_rgb():quality(40)/discogs-images/R-1249070-1446504539-8960.jpeg.jpg",
      "sectionNumber": 6,
      "remixArtistName": ""
    },
    {
      "publisher": "Atlantic Records",
      "startTime": "20:10",
      "trackName": "Spice Of Life",
      "artistName": "Manhattan Transfer",
      "coverArtDate": "2021-07-19 17:25:57",
      "coverArtLarge": "https://img.discogs.com/GSHR1UgrQhv3enzWeVTs_ZLPrsg=/fit-in/600x596/filters:strip_icc():format(jpeg):mode_rgb():quality(90)/discogs-images/R-650422-1498677323-2198.jpeg.jpg",
      "coverArtSmall": "https://img.discogs.com/zYd1kULI3Sk302Pw_XQLH_c0zsU=/fit-in/150x150/filters:strip_icc():format(jpeg):mode_rgb():quality(40)/discogs-images/R-650422-1498677323-2198.jpeg.jpg",
      "sectionNumber": 7,
      "remixArtistName": ""
    },
    {
      "publisher": "Epic",
      "startTime": "23:36",
      "trackName": "Off The Wall",
      "artistName": "Michael Jackson",
      "coverArtDate": "2021-07-19 17:26:00",
      "coverArtLarge": "https://img.discogs.com/PdQycnIURmp9Yjjfg9r6aIXls0U=/fit-in/600x575/filters:strip_icc():format(jpeg):mode_rgb():quality(90)/discogs-images/R-120096-1579720042-1723.jpeg.jpg",
      "coverArtSmall": "https://img.discogs.com/O3N0Adlybe1qjJkESeMB_DiPddc=/fit-in/150x150/filters:strip_icc():format(jpeg):mode_rgb():quality(40)/discogs-images/R-120096-1579720042-1723.jpeg.jpg",
      "sectionNumber": 8,
      "remixArtistName": ""
    },
    {
      "publisher": "A&M Records",
      "startTime": "26:37",
      "trackName": "Razzamatazz",
      "artistName": "Quincy Jones",
      "coverArtDate": "2021-07-19 17:26:03",
      "coverArtLarge": "https://img.discogs.com/30D1MdiMJ5jYPGVR-BWLtE_l2_s=/fit-in/600x593/filters:strip_icc():format(jpeg):mode_rgb():quality(90)/discogs-images/R-834782-1188320475.jpeg.jpg",
      "coverArtSmall": "https://img.discogs.com/qkFTNkEQW1lCbpusAyPnjoc9e50=/fit-in/150x150/filters:strip_icc():format(jpeg):mode_rgb():quality(40)/discogs-images/R-834782-1188320475.jpeg.jpg",
      "sectionNumber": 9,
      "remixArtistName": ""
    },
    {
      "publisher": "Warner Bros. Records",
      "startTime": "28:08",
      "trackName": "Love X Love",
      "artistName": "George Benson",
      "coverArtDate": "2021-07-19 17:26:05",
      "coverArtLarge": "https://img.discogs.com/dd4OU2ndmyPz-8g1uQKzO9PjKgo=/fit-in/600x603/filters:strip_icc():format(jpeg):mode_rgb():quality(90)/discogs-images/R-1328502-1579498505-1254.jpeg.jpg",
      "coverArtSmall": "https://img.discogs.com/L0kcs7J1LW7syP5gm0dNgGmdNFE=/fit-in/150x150/filters:strip_icc():format(jpeg):mode_rgb():quality(40)/discogs-images/R-1328502-1579498505-1254.jpeg.jpg",
      "sectionNumber": 10,
      "remixArtistName": ""
    },
    {
      "publisher": "Warner Bros. Records",
      "startTime": "31:20",
      "trackName": "Give Me The Night",
      "artistName": "George Benson",
      "coverArtDate": "2021-07-19 17:26:08",
      "coverArtLarge": "https://img.discogs.com/7m0lUvKhxy1qpXlXSFKSEhz-cNQ=/fit-in/600x600/filters:strip_icc():format(jpeg):mode_rgb():quality(90)/discogs-images/R-6891706-1428949998-9645.png.jpg",
      "coverArtSmall": "https://img.discogs.com/auQdguNjEaff9D88yL878EY-cNM=/fit-in/150x150/filters:strip_icc():format(jpeg):mode_rgb():quality(40)/discogs-images/R-6891706-1428949998-9645.png.jpg",
      "sectionNumber": 11,
      "remixArtistName": ""
    },
    {
      "publisher": "GTO",
      "startTime": "34:15",
      "trackName": "Eyballin'",
      "artistName": "Heatwave",
      "coverArtDate": "2021-07-19 17:26:10",
      "coverArtLarge": null,
      "coverArtSmall": null,
      "sectionNumber": 12,
      "remixArtistName": ""
    },
    {
      "publisher": "GTO",
      "startTime": "37:09",
      "trackName": "The Groove Line",
      "artistName": "Heatwave",
      "coverArtDate": "2021-07-19 17:26:13",
      "coverArtLarge": "https://img.discogs.com/dCemcGmfgP5S9FGsDOegMLkMCFQ=/600x407/smart/filters:strip_icc():format(jpeg):mode_rgb():quality(90)/discogs-images/A-31546-1533174016-1966.jpeg.jpg",
      "coverArtSmall": "https://img.discogs.com/z8ttFeIa0bP5vjKFTwB-Ykekg0I=/150x150/smart/filters:strip_icc():format(jpeg):mode_rgb():quality(40)/discogs-images/A-31546-1533174016-1966.jpeg.jpg",
      "sectionNumber": 13,
      "remixArtistName": ""
    },
    {
      "publisher": "Qwest Records",
      "startTime": "40:48",
      "trackName": "Yah-Mo B There",
      "artistName": "James Ingram with Michael McDonald",
      "coverArtDate": "2021-07-19 17:26:15",
      "coverArtLarge": "https://img.discogs.com/BBr7xdgsqwFEbQEeVsvidAyEEQk=/fit-in/586x607/filters:strip_icc():format(jpeg):mode_rgb():quality(90)/discogs-images/R-1397569-1270807106.jpeg.jpg",
      "coverArtSmall": "https://img.discogs.com/W3BCsKVgqSrPStp-JtCMXr4BICg=/fit-in/150x150/filters:strip_icc():format(jpeg):mode_rgb():quality(40)/discogs-images/R-1397569-1270807106.jpeg.jpg",
      "sectionNumber": 14,
      "remixArtistName": ""
    },
    {
      "publisher": "Ariola",
      "startTime": "43:18",
      "trackName": "Masterjam",
      "artistName": "Rufus & Chaka Khan",
      "coverArtDate": "2021-07-19 17:26:18",
      "coverArtLarge": "https://img.discogs.com/YjN2LM4ZfolT2zX_opUmASlwJV4=/fit-in/300x300/filters:strip_icc():format(jpeg):mode_rgb():quality(90)/discogs-images/R-1496892-1224098332.jpeg.jpg",
      "coverArtSmall": "https://img.discogs.com/xUplLGCrUGoqa-eTN30CDqGe4YI=/fit-in/150x150/filters:strip_icc():format(jpeg):mode_rgb():quality(40)/discogs-images/R-1496892-1224098332.jpeg.jpg",
      "sectionNumber": 15,
      "remixArtistName": ""
    },
    {
      "publisher": "A&M Records",
      "startTime": "45:13",
      "trackName": "Light Up The Night",
      "artistName": "Brother Johnson",
      "coverArtDate": "2021-07-19 17:26:20",
      "coverArtLarge": "https://img.discogs.com/rqBCXG5ktIvIuUwUz-5m6sfG2Zk=/fit-in/600x598/filters:strip_icc():format(jpeg):mode_rgb():quality(90)/discogs-images/R-1098144-1259021601.jpeg.jpg",
      "coverArtSmall": "https://img.discogs.com/6KKjauusMSlvKWlJpV2qZUaaEzE=/fit-in/150x150/filters:strip_icc():format(jpeg):mode_rgb():quality(40)/discogs-images/R-1098144-1259021601.jpeg.jpg",
      "sectionNumber": 16,
      "remixArtistName": ""
    },
    {
      "publisher": "Qwest Records",
      "startTime": "47:22",
      "trackName": "Do You Love Me",
      "artistName": "Patti Austin",
      "coverArtDate": "2021-07-19 17:26:23",
      "coverArtLarge": "https://img.discogs.com/vTjdgYi7Y8t-KW7gQL2autUtkfY=/fit-in/600x600/filters:strip_icc():format(jpeg):mode_rgb():quality(90)/discogs-images/R-2600066-1501357693-8046.jpeg.jpg",
      "coverArtSmall": "https://img.discogs.com/959-rzHvYcuVP5jjCk_byQPvBGo=/fit-in/150x150/filters:strip_icc():format(jpeg):mode_rgb():quality(40)/discogs-images/R-2600066-1501357693-8046.jpeg.jpg",
      "sectionNumber": 17,
      "remixArtistName": ""
    },
    {
      "publisher": "Tappan Zee",
      "startTime": "50:37",
      "trackName": "Sign Of The Times",
      "artistName": "Bob Jones",
      "coverArtDate": "2021-07-19 17:26:26",
      "coverArtLarge": "https://img.discogs.com/UMC0dSD6YE_3twoCrZQSbbprDw8=/fit-in/600x600/filters:strip_icc():format(jpeg):mode_rgb():quality(90)/discogs-images/R-15908076-1600435178-9964.jpeg.jpg",
      "coverArtSmall": "https://img.discogs.com/8NnVVkABw2o4zYDk8XtuzXi9BUY=/fit-in/150x150/filters:strip_icc():format(jpeg):mode_rgb():quality(40)/discogs-images/R-15908076-1600435178-9964.jpeg.jpg",
      "sectionNumber": 18,
      "remixArtistName": ""
    },
    {
      "publisher": "A&M Records",
      "startTime": "53:36",
      "trackName": "The Dude",
      "artistName": "Quincy Jones",
      "coverArtDate": "2021-07-19 17:26:28",
      "coverArtLarge": "https://img.discogs.com/NY2Tg0t_Gl2pV06YvGhq1lXe4_4=/fit-in/600x600/filters:strip_icc():format(jpeg):mode_rgb():quality(90)/discogs-images/R-2761237-1391106802-2935.jpeg.jpg",
      "coverArtSmall": "https://img.discogs.com/Kh3fYl9SFNV-1nWwwBFAZoMowNM=/fit-in/150x150/filters:strip_icc():format(jpeg):mode_rgb():quality(40)/discogs-images/R-2761237-1391106802-2935.jpeg.jpg",
      "sectionNumber": 19,
      "remixArtistName": ""
    },
    {
      "publisher": "GTO",
      "startTime": "56:51",
      "trackName": "Ain't No Half Steppin'",
      "artistName": "Heatwave",
      "coverArtDate": "2021-07-19 17:26:31",
      "coverArtLarge": "https://img.discogs.com/YI2dRBZXUtPQFHd034xxEY1XBFI=/fit-in/600x600/filters:strip_icc():format(jpeg):mode_rgb():quality(90)/discogs-images/R-1107152-1304318433.jpeg.jpg",
      "coverArtSmall": "https://img.discogs.com/dHh7rUWjpJRrvHtonNhTSXNWYjA=/fit-in/150x150/filters:strip_icc():format(jpeg):mode_rgb():quality(40)/discogs-images/R-1107152-1304318433.jpeg.jpg",
      "sectionNumber": 20,
      "remixArtistName": ""
    },
    {
      "publisher": "GTO",
      "startTime": "59:53",
      "trackName": "Send Out For Sunshine",
      "artistName": "Heatwave",
      "coverArtDate": "2021-07-19 17:26:33",
      "coverArtLarge": "https://img.discogs.com/Y29QoWp8vKf3x_uqUYdk0bYJbWc=/fit-in/600x598/filters:strip_icc():format(jpeg):mode_rgb():quality(90)/discogs-images/R-490902-1458649116-9143.jpeg.jpg",
      "coverArtSmall": "https://img.discogs.com/lAV7PO_JVCQekfnjvQhsVlIP5wI=/fit-in/150x150/filters:strip_icc():format(jpeg):mode_rgb():quality(40)/discogs-images/R-490902-1458649116-9143.jpeg.jpg",
      "sectionNumber": 21,
      "remixArtistName": ""
    },
    {
      "publisher": "Ariola",
      "startTime": "1:03:53",
      "trackName": "Live In Me",
      "artistName": "Rufus & Chaka Khan",
      "coverArtDate": "2021-07-19 17:26:36",
      "coverArtLarge": "https://img.discogs.com/YjN2LM4ZfolT2zX_opUmASlwJV4=/fit-in/300x300/filters:strip_icc():format(jpeg):mode_rgb():quality(90)/discogs-images/R-1496892-1224098332.jpeg.jpg",
      "coverArtSmall": "https://img.discogs.com/xUplLGCrUGoqa-eTN30CDqGe4YI=/fit-in/150x150/filters:strip_icc():format(jpeg):mode_rgb():quality(40)/discogs-images/R-1496892-1224098332.jpeg.jpg",
      "sectionNumber": 22,
      "remixArtistName": ""
    },
    {
      "publisher": "Motown",
      "startTime": "1:07:41",
      "trackName": "Vibe",
      "artistName": "Zhane",
      "coverArtDate": "2021-07-19 17:26:38",
      "coverArtLarge": "https://img.discogs.com/FRmdzJUjwQaKMl3K_Mn4Fwe-JmI=/fit-in/541x477/filters:strip_icc():format(jpeg):mode_rgb():quality(90)/discogs-images/R-1162865-1255002769.jpeg.jpg",
      "coverArtSmall": "https://img.discogs.com/rZzKEdS_WPAVzyX0oD_94XftAvQ=/fit-in/150x150/filters:strip_icc():format(jpeg):mode_rgb():quality(40)/discogs-images/R-1162865-1255002769.jpeg.jpg",
      "sectionNumber": 23,
      "remixArtistName": ""
    },
    {
      "publisher": "MCA Records Ltd.",
      "startTime": "1:09:29",
      "trackName": "Sweet Freedom",
      "artistName": "Michael McDonald",
      "coverArtDate": "2021-07-19 17:26:41",
      "coverArtLarge": "https://img.discogs.com/iuL8_g96QxDxuDCoDNs7f-j7dik=/fit-in/600x596/filters:strip_icc():format(jpeg):mode_rgb():quality(90)/discogs-images/R-1449650-1351089650-8115.jpeg.jpg",
      "coverArtSmall": "https://img.discogs.com/wXgpBtzNChPkuxCSdnP7K0czF0A=/fit-in/150x150/filters:strip_icc():format(jpeg):mode_rgb():quality(40)/discogs-images/R-1449650-1351089650-8115.jpeg.jpg",
      "sectionNumber": 24,
      "remixArtistName": ""
    },
    {
      "publisher": "Epic",
      "startTime": "1:13:09",
      "trackName": "Lettin' It Loose",
      "artistName": "Heatwave",
      "coverArtDate": "2021-07-19 17:26:44",
      "coverArtLarge": "https://img.discogs.com/pABze7xZj6BSSUhMKf_YGuftx_A=/fit-in/600x600/filters:strip_icc():format(jpeg):mode_rgb():quality(90)/discogs-images/R-1484496-1242350269.jpeg.jpg",
      "coverArtSmall": "https://img.discogs.com/ajQaJIjQxfDPvQ5LieJ80Jmx8b0=/fit-in/150x150/filters:strip_icc():format(jpeg):mode_rgb():quality(40)/discogs-images/R-1484496-1242350269.jpeg.jpg",
      "sectionNumber": 25,
      "remixArtistName": ""
    },
    {
      "publisher": "Qwest Records",
      "startTime": "1:16:20",
      "trackName": "The Genie",
      "artistName": "Patti Austin",
      "coverArtDate": "2021-07-19 17:26:46",
      "coverArtLarge": "https://img.discogs.com/4FNeKckun2aPt_dHy54rbMIgUsc=/fit-in/596x596/filters:strip_icc():format(jpeg):mode_rgb():quality(90)/discogs-images/R-2350606-1369306357-6738.jpeg.jpg",
      "coverArtSmall": "https://img.discogs.com/xa3DBFhUti-8saSzPFOObj9Nf_Y=/fit-in/150x150/filters:strip_icc():format(jpeg):mode_rgb():quality(40)/discogs-images/R-2350606-1369306357-6738.jpeg.jpg",
      "sectionNumber": 26,
      "remixArtistName": ""
    },
    {
      "publisher": "Epic",
      "startTime": "1:19:05",
      "trackName": "Thriller",
      "artistName": "Michael Jackson",
      "coverArtDate": "2021-07-19 17:26:49",
      "coverArtLarge": "https://img.discogs.com/7WGKGhsr4EkYJNQskB3nW-YdixI=/fit-in/600x602/filters:strip_icc():format(jpeg):mode_rgb():quality(90)/discogs-images/R-2911293-1594245812-7931.jpeg.jpg",
      "coverArtSmall": "https://img.discogs.com/XOmlYMla7xMzb382QAD76X3Feqg=/fit-in/150x150/filters:strip_icc():format(jpeg):mode_rgb():quality(40)/discogs-images/R-2911293-1594245812-7931.jpeg.jpg",
      "sectionNumber": 27,
      "remixArtistName": ""
    },
    {
      "publisher": "WEA International Inc.",
      "startTime": "1:22:35",
      "trackName": "Love Is In Control",
      "artistName": "Donna Summer",
      "coverArtDate": "2021-07-19 17:26:52",
      "coverArtLarge": "https://img.discogs.com/8j_tG-B1I4aZtXLyY5VgCUXzBUI=/fit-in/600x600/filters:strip_icc():format(jpeg):mode_rgb():quality(90)/discogs-images/R-564271-1329510709.jpeg.jpg",
      "coverArtSmall": "https://img.discogs.com/l7Bm9pG_0LPYF27V-STFOgfYTKY=/fit-in/150x150/filters:strip_icc():format(jpeg):mode_rgb():quality(40)/discogs-images/R-564271-1329510709.jpeg.jpg",
      "sectionNumber": 28,
      "remixArtistName": ""
    },
    {
      "publisher": "CBS",
      "startTime": "1:24:22",
      "trackName": "Lite Me Up",
      "artistName": "Herbie Hancock",
      "coverArtDate": "2021-07-19 17:26:54",
      "coverArtLarge": "https://img.discogs.com/2qKWxK9jh7ed547gjxIcntsObYY=/fit-in/600x594/filters:strip_icc():format(jpeg):mode_rgb():quality(90)/discogs-images/R-1249070-1446504539-8960.jpeg.jpg",
      "coverArtSmall": "https://img.discogs.com/opTO7d8j0LgKUthBUkMlijUM8ow=/fit-in/150x150/filters:strip_icc():format(jpeg):mode_rgb():quality(40)/discogs-images/R-1249070-1446504539-8960.jpeg.jpg",
      "sectionNumber": 29,
      "remixArtistName": ""
    },
    {
      "publisher": "Epic",
      "startTime": "1:26:18",
      "trackName": "Rock With You",
      "artistName": "Michael Jackson",
      "coverArtDate": "2021-07-19 17:26:57",
      "coverArtLarge": "https://img.discogs.com/GKl6y9CpgElErqwm5lmacjVfQRI=/fit-in/600x592/filters:strip_icc():format(jpeg):mode_rgb():quality(90)/discogs-images/R-892043-1370936763-9313.jpeg.jpg",
      "coverArtSmall": "https://img.discogs.com/MIWKb-qGtI0VbOg1TiAYI8UqzOY=/fit-in/150x150/filters:strip_icc():format(jpeg):mode_rgb():quality(40)/discogs-images/R-892043-1370936763-9313.jpeg.jpg",
      "sectionNumber": 30,
      "remixArtistName": ""
    }
  ]
}